nonutils/__init__.py
nonutils/__version__.py
nonutils/command.py
nonutils/persistent.py
nonutils/service.py
nonutils/stringres.py
nonutils/internal_services/__init__.py
nonutils/internal_services/usage.py
nonutils-0.1a0.dist-info/LICENSE
nonutils-0.1a0.dist-info/METADATA
nonutils-0.1a0.dist-info/WHEEL
nonutils-0.1a0.dist-info/top_level.txt
nonutils-0.1a0.dist-info/RECORD
