Metadata-Version: 2.1
Name: nonutils
Version: 0.1a0
Summary: Unofficial utilities for nonebot2.
Home-page: https://github.com/233a344a455/nonutils
Author: DeltaZero
Author-email: 233a344a455@gmail.com
License: MIT
Platform: UNKNOWN
Classifier: License :: OSI Approved :: MIT License
Classifier: Topic :: Utilities
Classifier: Development Status :: 3 - Alpha
Classifier: Programming Language :: Python
Classifier: Programming Language :: Python :: 3
Classifier: Programming Language :: Python :: 3.7
Classifier: Programming Language :: Python :: Implementation :: CPython
Classifier: Programming Language :: Python :: Implementation :: PyPy
Requires-Python: >=3.7.3
Requires-Dist: nonebot2
Requires-Dist: loguru
Requires-Dist: pydantic
